{"skeleton":{"hash":"BlvHZv3uaBB2JpeGDhm4aw+20B0","spine":"3.7.94","width":159,"height":121,"images":"./images/","audio":"D:/bp/New folder/ani/animation scarab"},"bones":[{"name":"root"},{"name":"bone2","parent":"root","x":-0.29,"y":-0.18},{"name":"thân","parent":"root","length":44.4,"rotation":100.57,"x":-2.33,"y":19.31},{"name":"đầu","parent":"thân","length":60.52,"rotation":-0.88,"x":32.77,"y":-5.23},{"name":"tay 2","parent":"thân","length":16.31,"rotation":-116.1,"x":25.99,"y":-24.09},{"name":"tay 3","parent":"tay 2","length":9.73,"rotation":-23.4,"x":16.31},{"name":"tay 1","parent":"thân","length":11.6,"rotation":117.37,"x":32.38,"y":28.17},{"name":"tay 4","parent":"tay 1","length":9.22,"rotation":25.06,"x":11.6},{"name":"chân 2","parent":"thân","length":13.96,"rotation":-176.1,"x":4.7,"y":-17.02},{"name":"chân 3","parent":"chân 2","length":12.52,"rotation":-21.47,"x":13.96},{"name":"chân 1","parent":"thân","length":12.97,"rotation":144.58,"x":6.24,"y":9.08},{"name":"chân 4","parent":"chân 1","length":9.03,"rotation":16.52,"x":12.97},{"name":"eye 1","parent":"đầu","length":25.16,"rotation":78.84,"x":29.2,"y":22.24},{"name":"eye 2","parent":"đầu","length":30.33,"rotation":-98.06,"x":24.6,"y":-4.68},{"name":"dote 2","parent":"đầu","length":18.77,"rotation":-5.09,"x":32.52,"y":-13.23},{"name":"dote 1","parent":"đầu","length":19.38,"rotation":-6.51,"x":37.45,"y":25.85},{"name":"mắt 2","parent":"đầu","length":12.9,"rotation":-9.69,"x":29.15,"y":-7.42},{"name":"mắt 1","parent":"đầu","length":15.92,"rotation":-12.01,"x":33.4,"y":21.3},{"name":"lm 2","parent":"đầu","length":11.41,"rotation":-6.45,"x":46.25,"y":-17.1},{"name":"lm 1","parent":"đầu","length":9.46,"rotation":-8.39,"x":52.41,"y":29.18},{"name":"râu 2","parent":"đầu","length":11.69,"rotation":-67.46,"x":48.21,"y":-23.54},{"name":"râu 3","parent":"râu 2","length":11.66,"rotation":-26.94,"x":11.69},{"name":"râu 1","parent":"đầu","length":10.55,"rotation":46.94,"x":55.83,"y":35.14},{"name":"râu 4","parent":"râu 1","length":7.95,"rotation":-56.63,"x":10.55},{"name":"cười","parent":"đầu","length":21.72,"rotation":169.74,"x":12.22,"y":9.65},{"name":"lưỡi","parent":"đầu","length":19.35,"rotation":171.58,"x":5.98,"y":13.99},{"name":"buồn","parent":"đầu","length":20.64,"rotation":-9.69,"x":12.06,"y":13.82},{"name":"Layer 7","parent":"đầu","length":41.95,"rotation":-3.51,"x":21.39,"y":58.25},{"name":"Layer 8","parent":"đầu","length":41.95,"rotation":-7.63,"x":21.14,"y":-56.87}],"slots":[{"name":"chân 1","bone":"chân 1","attachment":"chân 1"},{"name":"chân 2","bone":"chân 2","attachment":"chân 2"},{"name":"tay 1","bone":"tay 1","attachment":"tay 1"},{"name":"thân","bone":"thân","attachment":"thân"},{"name":"tay 2","bone":"tay 2","attachment":"tay 2"},{"name":"đầu","bone":"đầu","attachment":"đầu"},{"name":"cười","bone":"cười","attachment":"cười"},{"name":"lưỡi","bone":"lưỡi","attachment":"lưỡi"},{"name":"buồn","bone":"buồn","attachment":"buồn"},{"name":"lm 2","bone":"lm 2","attachment":"lm 2"},{"name":"lm 1","bone":"lm 1","attachment":"lm 1"},{"name":"eye 2","bone":"eye 2","attachment":"eye 2"},{"name":"dote 2","bone":"dote 2","attachment":"dote 2"},{"name":"mắt 2","bone":"mắt 2","attachment":"mắt 2"},{"name":"eye 1","bone":"eye 1","attachment":"eye 1"},{"name":"mắt 1","bone":"mắt 1","attachment":"mắt 1"},{"name":"dote 1","bone":"dote 1","attachment":"dote 1"},{"name":"râu 2","bone":"râu 2","attachment":"râu 2"},{"name":"râu 3","bone":"râu 2","attachment":"râu 2"},{"name":"râu 1","bone":"râu 1","attachment":"râu 1"},{"name":"Layer 7","bone":"Layer 7","attachment":"Layer 7"},{"name":"Layer 8","bone":"Layer 8","attachment":"Layer 8"}],"skins":{"default":{"Layer 7":{"Layer 7":{"x":8.78,"y":-52.41,"rotation":-96.18,"width":137,"height":39}},"Layer 8":{"Layer 8":{"x":-0.07,"y":61.4,"rotation":-92.06,"width":159,"height":60}},"buồn":{"buồn":{"x":1.09,"y":-5.79,"rotation":-90,"width":29,"height":15}},"chân 1":{"chân 1":{"type":"mesh","uvs":[0.01921,0.42051,0.03836,0.31578,0.0707,0.25978,0.11252,0.21299,0.18444,0.1827,0.31965,0.22989,0.35752,0.28932,0.36901,0.33161,0.37029,0.3939,0.36773,0.45447,0.36433,0.51161,0.32305,0.5659,0.29071,0.60933,0.25071,0.67333,0.17623,0.80819,0.07624,0.96591,0.05326,0.95677,0.03028,0.77887,0.02517,0.56856,0.04304,0.86973,0.01947,0.42688],"triangles":[17,18,13,14,17,13,19,17,14,15,16,19,17,19,16,14,15,19,4,5,6,7,4,6,8,2,3,8,3,4,7,8,4,1,2,8,9,0,1,9,20,0,1,8,9,9,11,20,10,11,9,18,20,11,20,17,0,12,18,11,13,18,12,17,20,18],"vertices":[2,10,9.64,-6.84,0.9974,11,-5.14,-5.61,0.0026,1,10,5.93,-7.56,1,1,10,3.52,-7.01,1,1,10,1.2,-5.91,1,1,10,-1.18,-3.29,1,1,10,-2.35,3.17,1,1,10,-1.21,5.66,1,1,10,-0.09,6.77,1,2,10,1.86,7.74,0.99804,11,-8.45,10.58,0.00196,2,10,3.83,8.52,0.98654,11,-6.34,10.77,0.01346,2,10,5.72,9.22,0.96657,11,-4.34,10.9,0.03343,2,10,8.26,8.26,0.8976,11,-2.17,9.26,0.1024,2,10,10.27,7.51,0.75801,11,-0.45,7.97,0.24199,2,10,13.1,6.75,0.42667,11,2.04,6.44,0.57333,2,10,18.85,5.56,0.00656,11,7.22,3.66,0.99344,1,11,13.36,-0.19,1,1,11,13.2,-1.31,1,1,11,7.19,-3.28,1,2,10,14.22,-4.41,0.5828,11,-0.06,-4.58,0.4172,1,11,10.25,-2.23,1,2,10,9.83,-6.74,0.99567,11,-4.92,-5.57,0.00433],"hull":18,"edges":[8,6,6,4,4,2,2,0,36,34,34,38,38,32,32,30,30,28,28,26,26,24,24,22,22,20,20,18,18,16,16,14,14,12,12,10,24,36,36,26,36,22,0,40,40,36,22,40,18,40,18,2,16,2,16,4,16,6,14,8,8,10,34,26,34,28,28,38,38,30,32,34,34,0],"width":47,"height":35}},"chân 2":{"chân 2":{"type":"mesh","uvs":[0.23379,0.14812,0.34714,0.11301,0.5807,0.09107,0.78336,0.13496,0.86922,0.21396,0.90357,0.30173,0.8967,0.44218,0.84175,0.75598,0.7387,0.85692,0.62192,0.95567,0.50514,0.96006,0.47766,0.88326,0.43988,0.80426,0.44675,0.71648,0.4021,0.62651,0.37118,0.56506,0.30936,0.50801,0.20288,0.48168,0.15136,0.3939,0.86579,0.57384],"triangles":[19,14,6,13,14,19,7,13,19,7,19,6,8,12,13,7,8,13,11,12,8,9,11,8,10,11,9,18,0,1,18,1,2,3,4,18,3,18,2,5,15,4,17,18,4,4,16,17,4,15,16,5,6,15,6,14,15],"vertices":[2,8,-1.67,-5.48,1,9,-12.53,-10.82,0,2,8,-2.24,-2.64,1,9,-14.11,-8.39,0,1,8,-1.66,2.76,1,1,8,1.03,6.87,1,1,8,4.28,8.08,1,2,8,7.54,8.05,1,9,-8.92,5.14,0,2,8,12.39,6.64,0.91283,9,-3.89,5.6,0.08717,1,9,7.48,5.72,1,1,9,11.38,3.82,1,1,9,15.23,1.58,1,1,9,15.72,-1.06,1,1,9,13.05,-2.03,1,1,9,10.33,-3.24,1,2,8,19.37,-5.85,0.00541,9,7.18,-3.47,0.99459,2,8,15.98,-6.04,0.15069,9,4.09,-4.88,0.84931,2,8,13.66,-6.17,0.44933,9,1.98,-5.86,0.55067,2,8,11.31,-7.04,0.78069,9,0.11,-7.52,0.21931,2,8,9.78,-9.17,0.90957,9,-0.53,-10.06,0.09043,2,8,6.43,-9.53,0.96662,9,-3.52,-11.62,0.03338,2,8,16.81,4.76,0.30722,9,0.91,5.47,0.69278],"hull":19,"edges":[36,34,34,32,32,30,30,28,28,26,26,24,24,22,22,20,20,18,18,16,16,14,14,38,38,12,12,10,10,8,8,6,6,4,4,2,2,0,0,36,28,12,30,12,30,10,32,8,8,36,8,34,36,6,36,2,26,38,14,26,26,16,16,24,22,16,22,18,12,14],"width":23,"height":36}},"cười":{"cười":{"x":3.77,"y":0.75,"rotation":90.57,"width":31,"height":15}},"dote 1":{"dote 1":{"x":0.11,"y":0.58,"rotation":-93.18,"width":12,"height":13}},"dote 2":{"dote 2":{"x":-0.22,"y":-1.06,"rotation":-94.6,"width":14,"height":14}},"eye 1":{"eye 1":{"x":4.6,"y":-2.99,"rotation":-178.53,"width":28,"height":28}},"eye 2":{"eye 2":{"x":10.3,"y":4.32,"rotation":-1.62,"width":32,"height":31}},"lm 1":{"lm 1":{"x":-0.14,"y":-1.22,"rotation":-91.3,"width":10,"height":9}},"lm 2":{"lm 2":{"x":0.64,"y":-0.61,"rotation":-93.24,"width":10,"height":10}},"lưỡi":{"lưỡi":{"x":3.46,"y":2.86,"rotation":88.73,"width":17,"height":12}},"mắt 1":{"mắt 1":{"x":1.49,"y":7.81,"rotation":-87.68,"width":22,"height":18}},"mắt 2":{"mắt 2":{"x":1.16,"y":-6.23,"rotation":-90,"width":22,"height":18}},"râu 1":{"râu 1":{"type":"mesh","uvs":[0.4397,0.07506,0.4429,0.13506,0.4493,0.27426,0.4685,0.35106,0.4685,0.39426,0.5805,0.45906,0.7117,0.52146,0.8717,0.61265,0.9517,0.66065,1,0.77105,0.9485,0.83105,0.8461,0.88865,0.7725,0.90065,0.6509,0.83825,0.4013,0.69185,0.2317,0.57905,0.13251,0.52626,0.11331,0.43026,0.10051,0.17346,0.11011,0.07746,0.22851,0,0.3533,0,0.5325,0.76145],"triangles":[21,0,1,20,21,1,19,20,1,18,19,1,18,1,2,17,18,2,17,2,3,17,3,4,15,16,17,4,15,17,14,15,4,14,4,5,22,14,5,22,5,6,10,7,8,10,8,9,13,22,6,13,6,7,7,12,13,14,22,13,10,11,7,11,12,7],"vertices":[1,23,7.72,-3.08,1,2,22,11.53,-7.17,0.00102,23,6.52,-3.13,0.99898,2,22,9.91,-4.9,0.10069,23,3.74,-3.23,0.89931,2,22,8.83,-3.77,0.34678,23,2.2,-3.52,0.65322,2,22,8.35,-3.05,0.5958,23,1.34,-3.52,0.4042,2,22,6.24,-2.89,0.95659,23,0.04,-5.2,0.04341,2,22,3.91,-2.93,0.99993,23,-1.21,-7.16,7.0E-5,1,22,0.9,-2.73,1,1,22,-0.63,-2.59,1,1,22,-2.45,-1.14,1,1,22,-2.46,0.29,1,1,22,-1.82,2.09,1,1,22,-1.03,2.9,1,1,22,1.18,2.86,1,1,22,5.92,2.47,1,2,22,9.29,1.99,0.97837,23,-2.36,0.04,0.02163,2,22,11.11,1.93,0.59991,23,-1.3,1.52,0.40009,2,22,12.41,0.48,0.02235,23,0.62,1.81,0.97765,1,23,5.75,2,1,1,23,7.67,1.86,1,1,23,9.22,0.08,1,1,23,9.22,-1.79,1,1,22,3.51,2.56,1],"hull":22,"edges":[40,42,36,34,34,32,32,30,30,28,28,44,44,26,26,24,24,22,22,20,20,18,18,16,16,14,14,12,12,10,10,8,8,6,6,4,4,2,2,0,0,42,40,38,38,36,8,30,8,28,10,28,10,44,12,44,12,26,14,26,14,22,14,20,16,20,8,34,6,34,4,34,2,36,36,4,2,40,2,38,42,2,26,28],"width":15,"height":20}},"râu 2":{"râu 2":{"type":"mesh","uvs":[0.98687,0.0425,1,0.1253,1,0.2702,0.98106,0.37369,0.95886,0.41279,0.92872,0.43809,0.897,0.46569,0.85999,0.47029,0.82773,0.46799,0.80817,0.49559,0.77169,0.62209,0.75265,0.67959,0.69449,0.70719,0.67704,0.6014,0.6781,0.50019,0.69819,0.34839,0.72093,0.27249,0.7775,0.1667,0.85893,0.16899,0.89382,0.14829,0.93348,0.1184,0.93454,0.0586,0.9615,0],"triangles":[21,22,0,21,0,1,20,21,1,19,20,1,19,1,2,18,19,2,3,18,2,3,5,18,4,5,3,6,18,5,8,18,7,6,7,18,16,17,9,17,18,8,9,15,16,17,8,9,14,15,9,10,14,9,13,14,10,11,13,10,12,13,11],"vertices":[1,21,13.88,3.31,1,1,21,14.87,1.56,1,1,21,14.6,-1.33,1,1,21,12.77,-3.24,1,1,21,10.77,-3.84,1,2,20,17.07,-7.33,3.0E-5,21,8.11,-4.1,0.99997,2,20,14.44,-6.33,0.02572,21,5.31,-4.4,0.97428,2,20,11.67,-4.69,0.28338,21,2.1,-4.19,0.71662,2,20,9.32,-3.15,0.83191,21,-0.69,-3.89,0.16809,2,20,7.58,-2.71,0.9885,21,-2.44,-4.28,0.0115,1,20,3.55,-3.16,1,1,20,1.53,-3.25,1,1,20,-3.04,-1.02,1,1,20,-3.2,1.58,1,1,20,-2.04,3.25,1,1,20,1.06,4.88,1,1,20,3.54,5.11,1,1,20,8.83,4.28,1,1,21,2.56,1.82,1,1,21,5.62,1.95,1,1,21,9.12,2.23,1,1,21,9.32,3.41,1,1,21,11.76,4.36,1],"hull":23,"edges":[4,2,22,20,20,18,18,16,16,14,14,12,12,10,10,8,8,6,6,4,2,0,0,44,44,42,42,40,40,38,38,36,36,34,34,32,32,30,30,28,28,26,26,24,16,34,16,36,12,36,36,14,34,18,18,32,30,18,18,28,28,20,20,26,26,22,22,24,6,36,4,38,40,2,2,38,2,42,42,0,36,4],"width":87,"height":20}},"râu 3":{"râu 2":{"type":"mesh","uvs":[0.98687,0.0425,1,0.1253,1,0.2702,0.98106,0.37369,0.95886,0.41279,0.92872,0.43809,0.897,0.46569,0.85999,0.47029,0.82773,0.46799,0.80817,0.49559,0.77169,0.62209,0.75265,0.67959,0.69449,0.70719,0.67704,0.6014,0.6781,0.50019,0.69819,0.34839,0.72093,0.27249,0.7775,0.1667,0.85893,0.16899,0.89382,0.14829,0.93348,0.1184,0.93454,0.0586,0.9615,0],"triangles":[21,22,0,21,0,1,20,21,1,19,20,1,19,1,2,18,19,2,3,18,2,3,5,18,4,5,3,6,18,5,8,18,7,6,7,18,16,17,9,17,18,8,9,15,16,17,8,9,14,15,9,10,14,9,13,14,10,11,13,10,12,13,11],"vertices":[1,21,13.88,3.31,1,1,21,14.87,1.56,1,1,21,14.6,-1.33,1,1,21,12.77,-3.24,1,1,21,10.77,-3.84,1,2,20,17.07,-7.33,3.0E-5,21,8.11,-4.1,0.99997,2,20,14.44,-6.33,0.02572,21,5.31,-4.4,0.97428,2,20,11.67,-4.69,0.28338,21,2.1,-4.19,0.71662,2,20,9.32,-3.15,0.83191,21,-0.69,-3.89,0.16809,2,20,7.58,-2.71,0.9885,21,-2.44,-4.28,0.0115,1,20,3.55,-3.16,1,1,20,1.53,-3.25,1,1,20,-3.04,-1.02,1,1,20,-3.2,1.58,1,1,20,-2.04,3.25,1,1,20,1.06,4.88,1,1,20,3.54,5.11,1,1,20,8.83,4.28,1,1,21,2.56,1.82,1,1,21,5.62,1.95,1,1,21,9.12,2.23,1,1,21,9.32,3.41,1,1,21,11.76,4.36,1],"hull":23,"edges":[4,2,22,20,20,18,18,16,16,14,14,12,12,10,10,8,8,6,6,4,2,0,0,44,44,42,42,40,40,38,38,36,36,34,34,32,32,30,30,28,28,26,26,24,16,34,16,36,12,36,36,14,34,18,18,32,30,18,18,28,28,20,20,26,26,22,22,24,6,36,4,38,40,2,2,38,2,42,42,0,36,4],"width":87,"height":20}},"tay 1":{"tay 1":{"type":"mesh","uvs":[0.05978,0.75464,0.07263,0.56682,0.1562,0.43378,0.25477,0.28509,0.56334,0.0777,0.67905,0.0327,0.83333,0.03662,0.87833,0.06009,0.9469,0.12857,0.94262,0.18335,0.91047,0.28118,0.84833,0.37313,0.76048,0.45335,0.64691,0.5766,0.53977,0.67247,0.43262,0.8016,0.33191,0.87986,0.24191,0.93464,0.1712,0.94051,0.1112,0.91899,0.0662,0.87008,0.40048,0.18726,0.54002,0.09339],"triangles":[14,2,3,1,2,14,1,16,0,14,15,1,0,19,20,1,15,16,19,0,18,16,17,0,17,18,0,9,7,8,4,22,3,10,7,9,6,7,10,5,6,10,22,21,3,11,5,10,4,5,11,22,4,11,12,22,11,21,22,12,13,21,12,3,21,13,13,14,3],"vertices":[1,7,9.56,-2.09,1,1,7,5.59,-3.81,1,2,6,15.01,-2.42,0.04969,7,2.07,-3.63,0.95031,2,6,11.27,-3.84,0.77257,7,-1.92,-3.34,0.22743,1,6,3.23,-3.62,1,1,6,0.68,-2.94,1,1,6,-1.82,-0.88,1,1,6,-2.24,0.13,1,1,6,-2.4,2.26,1,1,6,-1.56,3.2,1,1,6,0.36,4.56,1,2,6,2.69,5.42,0.99597,7,-5.77,8.68,0.00403,2,6,5.28,5.74,0.94985,7,-3.29,7.88,0.05015,2,6,8.9,6.51,0.68176,7,0.32,7.04,0.31824,2,6,12.03,6.87,0.29141,7,3.3,6.04,0.70859,2,6,15.63,7.83,0.03769,7,6.97,5.38,0.96231,2,6,18.41,7.94,0.00179,7,9.54,4.31,0.99821,1,7,11.52,3.2,1,1,7,12.31,1.94,1,1,7,12.44,0.59,1,1,7,11.87,-0.76,1,2,6,7.48,-3.73,0.99997,7,-5.31,-1.64,3.0E-5,1,6,3.84,-3.63,1],"hull":21,"edges":[10,8,42,6,6,4,4,2,2,0,0,40,40,38,38,36,36,34,34,32,32,30,30,28,28,26,26,24,24,22,22,20,20,18,18,16,16,14,14,12,12,10,26,42,26,6,28,6,28,4,28,2,30,2,2,32,32,0,0,34,36,0,0,38,8,44,44,42,24,44,24,42,44,22,22,10,20,12,20,14,20,10,22,8,6,8],"width":21,"height":23}},"tay 2":{"tay 2":{"type":"mesh","uvs":[0.05026,0.2783,0.09059,0.14497,0.17768,0.06164,0.28574,0.06164,0.45026,0.08386,0.55026,0.10331,0.65025,0.13664,0.75509,0.21997,0.84219,0.33108,0.88412,0.44497,0.93412,0.62552,0.95509,0.73385,0.9309,0.83663,0.89864,0.92274,0.84057,0.92274,0.73574,0.90607,0.5938,0.8144,0.53413,0.7533,0.42284,0.68941,0.30994,0.63107,0.15349,0.57552,0.03252,0.3783],"triangles":[8,17,7,9,17,8,10,17,9,16,17,10,10,15,16,10,11,15,12,15,11,12,14,15,13,14,12,1,2,3,0,1,3,21,0,3,20,21,3,19,3,4,20,3,19,19,4,5,18,19,5,18,5,6,18,6,7,17,18,7],"vertices":[1,4,-2.32,-1.33,1,1,4,-1.76,1.31,1,1,4,0.44,3.48,1,1,4,3.67,4.38,1,1,4,8.69,5.36,1,2,4,11.77,5.85,0.98367,5,-6.49,3.57,0.01633,2,4,14.92,6.1,0.80811,5,-3.7,5.05,0.19189,2,4,18.45,5.53,0.34155,5,-0.23,5.92,0.65845,2,4,21.59,4.32,0.04792,5,3.13,6.06,0.95208,2,4,23.39,2.69,0.00146,5,5.43,5.29,0.99854,1,5,8.68,3.73,1,1,5,10.41,2.62,1,1,5,10.99,0.71,1,1,5,11.18,-1.12,1,1,5,9.78,-2.25,1,2,4,21.18,-6.53,0.0064,5,7.07,-4.06,0.9936,2,4,16.5,-6.12,0.27271,5,2.61,-5.54,0.72729,2,4,14.42,-5.56,0.5756,5,0.48,-5.85,0.4244,2,4,10.79,-5.37,0.93371,5,-2.93,-7.12,0.06629,2,4,7.14,-5.3,0.99876,5,-6.31,-8.5,0.00124,1,4,2.2,-5.63,1,1,4,-2.37,-3.21,1],"hull":22,"edges":[42,40,40,38,38,36,36,34,34,32,32,30,30,28,28,26,26,24,24,22,22,20,20,18,18,16,16,14,14,12,12,10,10,8,8,6,6,4,4,2,2,0,0,42,36,12,36,14,34,14,34,18,34,16,32,20,20,30,20,34,22,30,28,24,38,6,38,10,38,8,40,6,6,0,6,42,6,2],"width":31,"height":18}},"thân":{"thân":{"type":"mesh","uvs":[1,1,0.31885,1,0,0.78423,0,0,1,0],"triangles":[1,2,3,4,1,3,1,4,0],"vertices":[-31.43,-44.76,-20.05,16.17,7.75,40.5,89.47,25.25,72.77,-64.21],"hull":5,"edges":[6,8,0,8,4,6,0,2,4,2],"width":91,"height":106}},"đầu":{"đầu":{"x":29.98,"y":5.39,"rotation":-99.69,"width":82,"height":73}}}},"animations":{"fun":{"slots":{"Layer 7":{"color":[{"time":0,"color":"ffffff00"}]},"Layer 8":{"color":[{"time":0,"color":"ffffff00"}]},"buồn":{"color":[{"time":0,"color":"ffffff00"}]},"dote 1":{"color":[{"time":0,"color":"ffffff00"}]},"dote 2":{"color":[{"time":0,"color":"ffffff00"}]},"eye 1":{"color":[{"time":0,"color":"ffffff00"}]},"eye 2":{"color":[{"time":0,"color":"ffffff00"}]},"lưỡi":{"color":[{"time":0,"color":"ffffff00"}]}},"bones":{"thân":{"translate":[{"time":0,"x":0,"y":0},{"time":0.1667,"x":0.62,"y":-3.31},{"time":0.3333,"x":0.47,"y":30.99},{"time":0.5,"x":4.89,"y":-3.8},{"time":0.6667,"x":4.21,"y":17.9},{"time":0.8333,"x":1.57,"y":-4.07},{"time":1,"x":0,"y":0}],"scale":[{"time":0,"x":1,"y":1},{"time":0.1667,"x":0.801,"y":1},{"time":0.3333,"x":1.057,"y":1},{"time":0.5,"x":0.813,"y":1},{"time":0.6667,"x":0.931,"y":1},{"time":0.8333,"x":0.808,"y":1},{"time":1,"x":1,"y":1}]},"chân 4":{"rotate":[{"time":0,"angle":0},{"time":0.3333,"angle":52.14},{"time":0.5,"angle":23.83},{"time":0.6667,"angle":-11.15},{"time":0.8333,"angle":31.05},{"time":1,"angle":0}]},"chân 2":{"rotate":[{"time":0,"angle":0},{"time":0.3333,"angle":-13.75},{"time":0.5,"angle":-11.5},{"time":0.6667,"angle":28.07},{"time":0.8333,"angle":5.34},{"time":1,"angle":0}],"translate":[{"time":0,"x":0,"y":0},{"time":0.1667,"x":-1.1,"y":-0.45},{"time":0.5,"x":-1.69,"y":-1.61},{"time":0.6667,"x":2.44,"y":-6.07},{"time":0.8333,"x":-1.34,"y":-1.98},{"time":1,"x":0,"y":0}]},"chân 3":{"rotate":[{"time":0,"angle":0},{"time":0.1667,"angle":-12.97},{"time":0.3333,"angle":24.06},{"time":0.5,"angle":-6.5},{"time":0.6667,"angle":-47.08},{"time":0.8333,"angle":-22.08},{"time":1,"angle":0}]},"chân 1":{"rotate":[{"time":0,"angle":0},{"time":0.3333,"angle":-41.71},{"time":0.5,"angle":7.42},{"time":0.6667,"angle":34.51},{"time":0.8333,"angle":3.64},{"time":1,"angle":0}],"translate":[{"time":0,"x":0,"y":0},{"time":0.3333,"x":1.02,"y":5.51},{"time":0.5,"x":-0.04,"y":2.13},{"time":0.6667,"x":-0.33,"y":1.95},{"time":1,"x":0,"y":0}]},"tay 2":{"rotate":[{"time":0,"angle":-28.39},{"time":0.1667,"angle":60.95},{"time":0.4333,"angle":-22.7},{"time":0.6667,"angle":47.12},{"time":1,"angle":-28.39}]},"tay 3":{"rotate":[{"time":0,"angle":-28.39},{"time":0.1667,"angle":60.95},{"time":0.4333,"angle":-22.7},{"time":0.6667,"angle":47.12},{"time":1,"angle":-28.39}]},"tay 1":{"rotate":[{"time":0,"angle":20.9},{"time":0.1667,"angle":-62.13},{"time":0.4,"angle":16.9},{"time":0.6667,"angle":-55.11},{"time":1,"angle":20.9}]},"tay 4":{"rotate":[{"time":0,"angle":20.9},{"time":0.1667,"angle":-62.13},{"time":0.4,"angle":16.9},{"time":0.6667,"angle":-55.11},{"time":1,"angle":20.9}]},"cười":{"translate":[{"time":0,"x":0,"y":0},{"time":0.3333,"x":3.95,"y":-0.72},{"time":0.6667,"x":0.24,"y":-1.02},{"time":1,"x":0,"y":0}],"scale":[{"time":0,"x":1,"y":1},{"time":0.3333,"x":1.369,"y":1.34},{"time":0.6667,"x":1,"y":1}]},"râu 1":{"rotate":[{"time":0,"angle":0},{"time":0.2667,"angle":-26.61},{"time":0.5,"angle":51.72},{"time":0.7333,"angle":-22.66},{"time":1,"angle":0}]},"râu 4":{"rotate":[{"time":0,"angle":0},{"time":0.2667,"angle":1.48},{"time":0.5,"angle":76.5},{"time":0.7333,"angle":8.32},{"time":1,"angle":0}]},"râu 2":{"rotate":[{"time":0,"angle":0},{"time":0.2667,"angle":31.9},{"time":0.5,"angle":-12.79},{"time":0.7667,"angle":27.68},{"time":1,"angle":0}]},"râu 3":{"rotate":[{"time":0,"angle":0},{"time":0.2667,"angle":31.9},{"time":0.5,"angle":-1.05},{"time":0.7667,"angle":28.95},{"time":1,"angle":0}]}}},"sad":{"slots":{"Layer 7":{"color":[{"time":0,"color":"ffffff00","curve":"stepped"},{"time":0.1333,"color":"ffffff00"},{"time":0.1667,"color":"ffffffff","curve":"stepped"},{"time":0.3,"color":"ffffffff"},{"time":0.3333,"color":"ffffff00"}]},"Layer 8":{"color":[{"time":0,"color":"ffffff00","curve":"stepped"},{"time":0.3,"color":"ffffff00"},{"time":0.3333,"color":"ffffffff"},{"time":0.3667,"color":"ffffff00"}]},"cười":{"color":[{"time":0,"color":"ffffff00"}]},"dote 1":{"color":[{"time":0.1333,"color":"ffffffff"},{"time":0.1667,"color":"ffffff00","curve":"stepped"},{"time":0.8,"color":"ffffff00"},{"time":0.8333,"color":"ffffffff"}]},"dote 2":{"color":[{"time":0.1333,"color":"ffffffff"},{"time":0.1667,"color":"ffffff00","curve":"stepped"},{"time":0.8,"color":"ffffff00"},{"time":0.8333,"color":"ffffffff"}]},"eye 1":{"color":[{"time":0.1333,"color":"ffffffff"},{"time":0.1667,"color":"ffffff00","curve":"stepped"},{"time":0.8,"color":"ffffff00"},{"time":0.8333,"color":"ffffffff"}]},"eye 2":{"color":[{"time":0.1333,"color":"ffffffff"},{"time":0.1667,"color":"ffffff00","curve":"stepped"},{"time":0.8,"color":"ffffff00"},{"time":0.8333,"color":"ffffffff"}]},"lưỡi":{"color":[{"time":0,"color":"ffffff00"}]},"mắt 1":{"color":[{"time":0,"color":"ffffff00","curve":"stepped"},{"time":0.1333,"color":"ffffff00"},{"time":0.1667,"color":"ffffffff","curve":"stepped"},{"time":0.8,"color":"ffffffff"},{"time":0.8333,"color":"ffffff00"}]},"mắt 2":{"color":[{"time":0,"color":"ffffff00","curve":"stepped"},{"time":0.1333,"color":"ffffff00"},{"time":0.1667,"color":"ffffffff","curve":"stepped"},{"time":0.8,"color":"ffffffff"},{"time":0.8333,"color":"ffffff00"}]}},"bones":{"mắt 1":{"translate":[{"time":0.1667,"x":0,"y":0},{"time":0.3333,"x":-3.84,"y":-18.05},{"time":0.5,"x":2.73,"y":12.83,"curve":"stepped"},{"time":0.6667,"x":2.73,"y":12.83},{"time":0.8333,"x":0,"y":0}]},"mắt 2":{"translate":[{"time":0.1667,"x":0,"y":0},{"time":0.3333,"x":-2.54,"y":-14.87},{"time":0.5,"x":3.15,"y":18.42,"curve":"stepped"},{"time":0.6667,"x":3.15,"y":18.42},{"time":0.8333,"x":0,"y":0}]},"buồn":{"translate":[{"time":0.1667,"x":0,"y":0},{"time":0.3333,"x":-2.8,"y":-16.39},{"time":0.5,"x":3.18,"y":18.62,"curve":"stepped"},{"time":0.6667,"x":3.18,"y":18.62},{"time":0.8333,"x":0,"y":0}],"scale":[{"time":0,"x":1,"y":1},{"time":0.1667,"x":1.64,"y":1.054},{"time":0.3333,"x":1,"y":1}]},"thân":{"translate":[{"time":0,"x":0,"y":0},{"time":0.2333,"x":0.33,"y":-2.5},{"time":0.4333,"x":1.85,"y":9.7},{"time":0.6,"x":3.89,"y":-3.86},{"time":0.8333,"x":0,"y":0}],"scale":[{"time":0,"x":1,"y":1},{"time":0.2333,"x":0.878,"y":1},{"time":0.4333,"x":1.012,"y":1},{"time":0.6,"x":0.866,"y":1},{"time":0.8333,"x":1,"y":1}]},"chân 4":{"rotate":[{"time":0,"angle":0},{"time":0.2333,"angle":32.8},{"time":0.4333,"angle":-6.89},{"time":0.6,"angle":39.15},{"time":0.8333,"angle":0}]},"chân 3":{"rotate":[{"time":0,"angle":0},{"time":0.2333,"angle":-22.37},{"time":0.4333,"angle":25.9},{"time":0.6,"angle":-26.92},{"time":0.8333,"angle":0}]},"tay 1":{"rotate":[{"time":0,"angle":0},{"time":0.2333,"angle":26.83},{"time":0.4333,"angle":-60.33},{"time":0.6,"angle":31},{"time":0.8333,"angle":0}]},"tay 4":{"rotate":[{"time":0,"angle":0},{"time":0.2333,"angle":26.83},{"time":0.4333,"angle":-60.33},{"time":0.6,"angle":31},{"time":0.8333,"angle":0}]},"tay 2":{"rotate":[{"time":0,"angle":0},{"time":0.2333,"angle":-33.27},{"time":0.4333,"angle":49.2},{"time":0.6,"angle":-30.37},{"time":0.8333,"angle":0}]},"tay 3":{"rotate":[{"time":0,"angle":0},{"time":0.2333,"angle":-33.27},{"time":0.4333,"angle":49.2},{"time":0.6,"angle":-30.37},{"time":0.8333,"angle":0}]},"râu 2":{"rotate":[{"time":0,"angle":0},{"time":0.2333,"angle":31.9},{"time":0.4333,"angle":-12.79},{"time":0.6667,"angle":27.68},{"time":0.8333,"angle":0}]},"râu 3":{"rotate":[{"time":0,"angle":0},{"time":0.2333,"angle":31.9},{"time":0.4333,"angle":-1.05},{"time":0.6667,"angle":28.95},{"time":0.8333,"angle":0}]},"râu 1":{"rotate":[{"time":0,"angle":0},{"time":0.2333,"angle":-26.61},{"time":0.4,"angle":51.72},{"time":0.6,"angle":-22.66},{"time":0.8333,"angle":0}]},"râu 4":{"rotate":[{"time":0,"angle":0},{"time":0.2333,"angle":1.48},{"time":0.4,"angle":76.5},{"time":0.6,"angle":8.32},{"time":0.8333,"angle":0}]},"lm 2":{"translate":[{"time":0,"x":0,"y":0},{"time":0.3333,"x":-5.23,"y":-13.38},{"time":0.5,"x":1.93,"y":12.91,"curve":"stepped"},{"time":0.6667,"x":1.93,"y":12.91},{"time":0.8333,"x":0,"y":0}]},"lm 1":{"translate":[{"time":0,"x":0,"y":0},{"time":0.3333,"x":-2.86,"y":-20.55},{"time":0.5,"x":2.13,"y":5.27,"curve":"stepped"},{"time":0.6667,"x":2.13,"y":5.27},{"time":0.8333,"x":0,"y":0}]}}},"stand":{"slots":{"Layer 7":{"color":[{"time":0,"color":"ffffff00"}]},"Layer 8":{"color":[{"time":0,"color":"ffffff00"}]},"buồn":{"color":[{"time":0,"color":"ffffff00"}]},"dote 1":{"color":[{"time":0.4667,"color":"ffffffff"},{"time":0.5,"color":"ffffff00","curve":"stepped"},{"time":0.6333,"color":"ffffff00"},{"time":0.6667,"color":"ffffffff","curve":"stepped"},{"time":1.1333,"color":"ffffffff"},{"time":1.1667,"color":"ffffff00","curve":"stepped"},{"time":1.3,"color":"ffffff00"},{"time":1.3333,"color":"ffffffff"}]},"dote 2":{"color":[{"time":0.4667,"color":"ffffffff"},{"time":0.5,"color":"ffffff00","curve":"stepped"},{"time":0.6333,"color":"ffffff00"},{"time":0.6667,"color":"ffffffff","curve":"stepped"},{"time":1.1333,"color":"ffffffff"},{"time":1.1667,"color":"ffffff00","curve":"stepped"},{"time":1.3,"color":"ffffff00"},{"time":1.3333,"color":"ffffffff"}]},"eye 1":{"color":[{"time":0.4667,"color":"ffffffff"},{"time":0.5,"color":"ffffff00","curve":"stepped"},{"time":0.6333,"color":"ffffff00"},{"time":0.6667,"color":"ffffffff","curve":"stepped"},{"time":1.1333,"color":"ffffffff"},{"time":1.1667,"color":"ffffff00","curve":"stepped"},{"time":1.3,"color":"ffffff00"},{"time":1.3333,"color":"ffffffff"}]},"eye 2":{"color":[{"time":0.4667,"color":"ffffffff"},{"time":0.5,"color":"ffffff00","curve":"stepped"},{"time":0.6333,"color":"ffffff00"},{"time":0.6667,"color":"ffffffff","curve":"stepped"},{"time":1.1333,"color":"ffffffff"},{"time":1.1667,"color":"ffffff00","curve":"stepped"},{"time":1.3,"color":"ffffff00"},{"time":1.3333,"color":"ffffffff"}]},"lưỡi":{"color":[{"time":0,"color":"ffffff00"}]},"mắt 1":{"color":[{"time":0,"color":"ffffff00"},{"time":0.4667,"color":"ffffff00"},{"time":0.5,"color":"ffffffff","curve":"stepped"},{"time":0.6333,"color":"ffffffff"},{"time":0.6667,"color":"ffffff00","curve":"stepped"},{"time":1.1333,"color":"ffffff00"},{"time":1.1667,"color":"ffffffff","curve":"stepped"},{"time":1.3,"color":"ffffffff"},{"time":1.3333,"color":"ffffff00"}]},"mắt 2":{"color":[{"time":0,"color":"ffffff00","curve":"stepped"},{"time":0.4667,"color":"ffffff00"},{"time":0.5,"color":"fffffffe","curve":"stepped"},{"time":0.6333,"color":"fffffffe"},{"time":0.6667,"color":"ffffff00","curve":"stepped"},{"time":1.1333,"color":"ffffff00"},{"time":1.1667,"color":"fffffffe","curve":"stepped"},{"time":1.3,"color":"fffffffe"},{"time":1.3333,"color":"ffffff00"}]}},"bones":{"mắt 2":{"translate":[{"time":0,"x":0,"y":0},{"time":0.5,"x":-1.63,"y":-9.52},{"time":1.1667,"x":2.39,"y":14.02}]},"mắt 1":{"translate":[{"time":0,"x":0,"y":0},{"time":0.5,"x":-2.41,"y":-11.34},{"time":1.1667,"x":2.04,"y":9.58}]},"thân":{"translate":[{"time":0,"x":0,"y":0},{"time":0.3333,"x":0.4,"y":-2.14},{"time":0.6667,"x":0,"y":0},{"time":1,"x":0.4,"y":-2.14},{"time":1.6667,"x":0,"y":0}],"scale":[{"time":0,"x":1,"y":1},{"time":0.3333,"x":0.86,"y":1},{"time":0.6667,"x":1,"y":1},{"time":1,"x":0.86,"y":1},{"time":1.6667,"x":1,"y":1}]},"eye 2":{"translate":[{"time":0,"x":0,"y":0},{"time":0.1667,"x":-1.26,"y":-8.87},{"time":0.4667,"x":-0.61,"y":-4.54,"curve":"stepped"},{"time":0.8333,"x":-0.61,"y":-4.54},{"time":1,"x":2.23,"y":14.53,"curve":"stepped"},{"time":1.3333,"x":2.23,"y":14.53},{"time":1.6667,"x":0,"y":0}]},"dote 2":{"translate":[{"time":0,"x":0,"y":0},{"time":0.1667,"x":-2.89,"y":-17.26},{"time":0.4667,"x":-1.91,"y":-10.91,"curve":"stepped"},{"time":0.8333,"x":-1.91,"y":-10.91},{"time":1,"x":1.55,"y":17.71,"curve":"stepped"},{"time":1.3333,"x":1.55,"y":17.71},{"time":1.6667,"x":0,"y":0}]},"eye 1":{"translate":[{"time":0,"x":0,"y":0},{"time":0.1667,"x":-1.97,"y":-12.13},{"time":0.4667,"x":-1.1,"y":-7.74,"curve":"stepped"},{"time":0.8333,"x":-1.1,"y":-7.74},{"time":1,"x":2.89,"y":12.52,"curve":"stepped"},{"time":1.3333,"x":2.89,"y":12.52},{"time":1.6667,"x":0,"y":0}]},"dote 1":{"translate":[{"time":0,"x":0,"y":0},{"time":0.1667,"x":-4.08,"y":-16.44},{"time":0.4667,"x":-3.05,"y":-10.45,"curve":"stepped"},{"time":0.8333,"x":-3.05,"y":-10.45},{"time":1,"x":1.35,"y":15.96,"curve":"stepped"},{"time":1.3333,"x":1.35,"y":15.96},{"time":1.6667,"x":0,"y":0}]},"cười":{"rotate":[{"time":0,"angle":0.7}],"translate":[{"time":0,"x":0,"y":0},{"time":0.5,"x":-2.1,"y":-11.28},{"time":0.6333,"x":0.95,"y":-12.75},{"time":0.6667,"x":-1.69,"y":-10.73},{"time":0.8333,"x":-2.26,"y":-12.17},{"time":1,"x":1.69,"y":9.68,"curve":"stepped"},{"time":1.3333,"x":1.69,"y":9.68},{"time":1.6667,"x":0,"y":0}],"scale":[{"time":0,"x":1,"y":1},{"time":0.6333,"x":0.329,"y":1},{"time":0.8333,"x":1,"y":1}]},"lm 2":{"translate":[{"time":0,"x":-0.25,"y":0.04},{"time":0.5,"x":-2.55,"y":-12.27,"curve":"stepped"},{"time":0.8333,"x":-2.55,"y":-12.27},{"time":1,"x":-0.97,"y":1.73},{"time":1.6667,"x":-0.25,"y":0.04}]},"lm 1":{"translate":[{"time":0,"x":0,"y":0},{"time":0.5,"x":-2.8,"y":-15.98,"curve":"stepped"},{"time":0.8333,"x":-2.8,"y":-15.98},{"time":1,"x":0.28,"y":4.94},{"time":1.6667,"x":0,"y":0}]},"tay 1":{"rotate":[{"time":0,"angle":0},{"time":0.3333,"angle":-34.99},{"time":0.6667,"angle":8.01},{"time":1,"angle":-30.89},{"time":1.6667,"angle":0}]},"tay 4":{"rotate":[{"time":0,"angle":0},{"time":0.3333,"angle":-34.99},{"time":0.6667,"angle":8.01},{"time":1,"angle":-30.89},{"time":1.6667,"angle":0}]},"tay 2":{"rotate":[{"time":0,"angle":0},{"time":0.3333,"angle":33.93},{"time":0.6667,"angle":-27.14},{"time":1,"angle":35.25},{"time":1.6667,"angle":0}]},"tay 3":{"rotate":[{"time":0,"angle":0},{"time":0.3333,"angle":33.93},{"time":0.6667,"angle":-27.14},{"time":1,"angle":35.25},{"time":1.6667,"angle":0}]},"râu 1":{"rotate":[{"time":0,"angle":0},{"time":0.3333,"angle":-26.61},{"time":0.6667,"angle":51.72},{"time":1,"angle":-22.66},{"time":1.6667,"angle":0}]},"râu 4":{"rotate":[{"time":0,"angle":0},{"time":0.3333,"angle":1.48},{"time":0.6667,"angle":76.5},{"time":1,"angle":8.32},{"time":1.6667,"angle":0}]},"râu 2":{"rotate":[{"time":0,"angle":0},{"time":0.3333,"angle":31.9},{"time":0.6667,"angle":-12.79},{"time":1,"angle":27.68},{"time":1.6667,"angle":0}]},"râu 3":{"rotate":[{"time":0,"angle":0},{"time":0.3333,"angle":31.9},{"time":0.6667,"angle":-1.05},{"time":1,"angle":28.95},{"time":1.6667,"angle":0}]}}}}}